kedro_viz_lite/__init__.py
kedro_viz_lite/_modidx.py
kedro_viz_lite/core.py
kedro_viz_lite-0.0.1.dist-info/LICENSE
kedro_viz_lite-0.0.1.dist-info/METADATA
kedro_viz_lite-0.0.1.dist-info/WHEEL
kedro_viz_lite-0.0.1.dist-info/entry_points.txt
kedro_viz_lite-0.0.1.dist-info/top_level.txt
kedro_viz_lite-0.0.1.dist-info/RECORD
