Metadata-Version: 2.1
Name: kedro-viz-lite
Version: 0.0.1
Summary: Run kedro-viz in a notebook without a full Kedro Project.
Home-page: https://github.com/noklam/kedro-viz-lite
Author: noklam
Author-email: mediumnok@gmail.com
License: Apache Software License 2.0
Keywords: nbdev jupyter notebook python kedro-viz kedro
Classifier: Development Status :: 4 - Beta
Classifier: Intended Audience :: Developers
Classifier: Natural Language :: English
Classifier: Programming Language :: Python :: 3.7
Classifier: Programming Language :: Python :: 3.8
Classifier: Programming Language :: Python :: 3.9
Classifier: Programming Language :: Python :: 3.10
Classifier: License :: OSI Approved :: Apache Software License
Requires-Python: >=3.7
License-File: LICENSE
Provides-Extra: dev
